[
    {
        "page": 1,
        "metadata": {
            "source": "C:\\Users\\ansh_lodhi\\Desktop\\BD_Assistant\\CaseStudies\\Case Study (80).pdf",
            "file_path": "C:\\Users\\ansh_lodhi\\Desktop\\BD_Assistant\\CaseStudies\\Case Study (80).pdf",
            "page": 0,
            "total_pages": 4,
            "format": "PDF 1.7",
            "title": "",
            "author": "Akhila Akula",
            "subject": "",
            "keywords": "",
            "creator": "Microsoft® PowerPoint® for Microsoft 365",
            "producer": "Microsoft® PowerPoint® for Microsoft 365",
            "creationDate": "D:20241114200013+05'30'",
            "modDate": "D:20241114200013+05'30'",
            "trapped": ""
        },
        "content": "© 2024 Accordion     CONFIDENTIAL\n© 2024 Accordion     CONFIDENTIAL\nSales incentive plan for BDMS\n1\nAnalyzed the current Incentive plan in place for BDMs (Business Development \nManagers) and proposed a revised plan intended to incentivize new customer \ngrowth\nIndustrial staffing company \n"
    },
    {
        "page": 2,
        "metadata": {
            "source": "C:\\Users\\ansh_lodhi\\Desktop\\BD_Assistant\\CaseStudies\\Case Study (80).pdf",
            "file_path": "C:\\Users\\ansh_lodhi\\Desktop\\BD_Assistant\\CaseStudies\\Case Study (80).pdf",
            "page": 1,
            "total_pages": 4,
            "format": "PDF 1.7",
            "title": "",
            "author": "Akhila Akula",
            "subject": "",
            "keywords": "",
            "creator": "Microsoft® PowerPoint® for Microsoft 365",
            "producer": "Microsoft® PowerPoint® for Microsoft 365",
            "creationDate": "D:20241114200013+05'30'",
            "modDate": "D:20241114200013+05'30'",
            "trapped": ""
        },
        "content": "© 2024 Accordion     CONFIDENTIAL\n© 2024 Accordion     CONFIDENTIAL\nAccordion Value Add \n•\nAnalyzed the historical Incentive pay outs of the BDMs to understand the current distribution of new and existing accounts vis-à-vis the incentive payouts. \n•\nDrafted a proforma incentive plan that focuses on driving New sales generation by setting higher incentive rates for new business and creating a variation in \nthe rates offered for “New” business vs. “Existing” business\n•\nAssessed the impact of the proposed incentive plan on the overall payouts with the incentives being based on book of business rather than customer level\nSituation\n•\nClient employs various Business Development Managers (BDMs) to drive new account generation and also manage relationships with current accounts \nensuring client retention. BDMs are incentivized based on the gross profit of their customers without differentiating new and retained accounts.\n•\nPartnered with the client to propose a new incentive plan focused on driving New account growth along with ensuring minimal BDM resistance to change \nin compensation structure\nDevelopment of sales incentive plan\n2\nImpact\n•\nProposed plan has a clear distinction between the incentive rates for New business vs. Existing business with minimal impact on the overall payouts\n•\nBased on assessment of the existing data, the proposed plan could potentially translate to an incremental annual revenue of ~$50M for the same amount of \nincentives paid to the BDMs as present.\nSales incentive plan for BDMS\n"
    },
    {
        "page": 3,
        "metadata": {
            "source": "C:\\Users\\ansh_lodhi\\Desktop\\BD_Assistant\\CaseStudies\\Case Study (80).pdf",
            "file_path": "C:\\Users\\ansh_lodhi\\Desktop\\BD_Assistant\\CaseStudies\\Case Study (80).pdf",
            "page": 2,
            "total_pages": 4,
            "format": "PDF 1.7",
            "title": "",
            "author": "Akhila Akula",
            "subject": "",
            "keywords": "",
            "creator": "Microsoft® PowerPoint® for Microsoft 365",
            "producer": "Microsoft® PowerPoint® for Microsoft 365",
            "creationDate": "D:20241114200013+05'30'",
            "modDate": "D:20241114200013+05'30'",
            "trapped": ""
        },
        "content": "© 2024 Accordion     CONFIDENTIAL\n© 2024 Accordion     CONFIDENTIAL\nApproach and methodology\n3\nDefine the expected share of New \nBusiness for the upcoming cycle as well \nas the expected retention rate of \npresent business during the next cycle\nDefine the expected gap in the average \nincentive rates for New and Existing \nBusiness\nDefine the proposed incentive rate for \nExisting business based on revised \nshare of business and expected spread\nAnalysis Approach\nDefine the proposed incentive rate for \nNew business using the proposed \nExisting rates and predefined gap \namong the two\nEstimates based on Proposed Incentive plan \nfor next cycle\nActuals based on existing Incentive plan for \ncurrent cycle\nExisting \nBusiness\nNew Business\nTotal\nExisting Business New Business\nTotal\nIncentive rates\n3.5%\n4.3%\n4.0%\n3.7%\n3.9%\n3.8%\nGP% - Below 8%\n0.0%\n0.0%\n0.0%\n0.0%\n0.0%\n0.0%\nGP% - 8-9.99%\n0.2%\n1.0%\n0.6%\n0.5%\n0.5%\n0.5%\nGP% - 10-11.99%\n0.9%\n1.7%\n1.4%\n1.2%\n1.5%\n1.4%\nGP% - 12-13.99%\n1.8%\n2.6%\n2.3%\n2.1%\n2.0%\n2.1%\nGP% - 14-15.99%\n2.7%\n3.5%\n3.1%\n3.0%\n3.1%\n3.0%\nGP% - 16-17.99%\n3.3%\n4.1%\n3.7%\n3.6%\n3.6%\n3.6%\nGP% - 18-19.99%\n3.8%\n4.6%\n4.2%\n4.1%\n4.1%\n4.1%\nGP% - 20-24.99%\n4.8%\n5.6%\n5.2%\n5.1%\n5.2%\n5.1%\nGP% - 25%+\n5.6%\n6.4%\n6.0%\n4.5%\n4.5%\n4.5%\nTargeted share of New business for next cycle\n55%\nTargeted retention rate of Overall business of last cycle as Base business for next cycle\n50%\nSpread distributed to Base\n40%\nEstimated difference in Incentive rates for New and Base business to achieve targeted mix of \nbusiness\n0.8%\n"
    },
    {
        "page": 4,
        "metadata": {
            "source": "C:\\Users\\ansh_lodhi\\Desktop\\BD_Assistant\\CaseStudies\\Case Study (80).pdf",
            "file_path": "C:\\Users\\ansh_lodhi\\Desktop\\BD_Assistant\\CaseStudies\\Case Study (80).pdf",
            "page": 3,
            "total_pages": 4,
            "format": "PDF 1.7",
            "title": "",
            "author": "Akhila Akula",
            "subject": "",
            "keywords": "",
            "creator": "Microsoft® PowerPoint® for Microsoft 365",
            "producer": "Microsoft® PowerPoint® for Microsoft 365",
            "creationDate": "D:20241114200013+05'30'",
            "modDate": "D:20241114200013+05'30'",
            "trapped": ""
        },
        "content": "© 2024 Accordion     CONFIDENTIAL\n© 2024 Accordion     CONFIDENTIAL\nIncentive structure designed to minimize resistance\n4\n60%\n48%\nActual\n52%\n40%\nProposed\n$4.0M\n$3.8M\n-2.6%\nScenario 1\n35%\n65%\n$4.1 M\nScenario 1\n50%\n$733 M\nActual\n50%\n46%\n54%\n$783 M\n+6.9%\nExisting Business\nNew business\nImpact of proposed plan \non $ Incentive\nImpact of incremental \nincentives on Revenue\nTotal incentives paid to \ncompensate the Reps with \ndeficit\nIncentives Paid\nRevenue\n•\nScenario 1 represents the total incentives paid \nassuming those who experienced a decline are \nmade whole\n•\nIf all BDMs were made whole the incremental \nincentives paid would amount to ~$300k under the \nnew plan\n•\nThis would translate to an incremental revenue of \n$50M \n"
    }
]